litrepl/__init__.py
litrepl/base.py
litrepl/eval.py
litrepl/main.py
litrepl/revision.py
litrepl/semver.py
litrepl/types.py
litrepl/utils.py
litrepl/interpreters/__init__.py
litrepl/interpreters/aicli.py
litrepl/interpreters/ipython.py
litrepl/interpreters/python.py
litrepl/interpreters/shell.py
litrepl-3.13.0.data/scripts/litrepl
litrepl-3.13.0.dist-info/LICENSE.txt
litrepl-3.13.0.dist-info/METADATA
litrepl-3.13.0.dist-info/WHEEL
litrepl-3.13.0.dist-info/top_level.txt
litrepl-3.13.0.dist-info/RECORD
