Metadata-Version: 2.1
Name: litrepl
Version: 3.13.0
Summary: Litrepl evaluates code from LaTeX/Markdown verbatim sections.
Home-page: https://github.com/sergei-mironov/litrepl
Author: Sergei Mironov
Author-email: sergei.v.mironov@proton.me
Classifier: Programming Language :: Python :: 3
Classifier: License :: OSI Approved :: Apache Software License
Classifier: Operating System :: POSIX :: Linux
Classifier: Topic :: Software Development :: Build Tools
Classifier: Intended Audience :: Developers
Classifier: Development Status :: 3 - Alpha
Requires-Python: >=3.6
License-File: LICENSE.txt
Requires-Dist: lark
Requires-Dist: psutil
